{
    "id": 1,
    "name": "Ma",
    "count": 4,
    "project_list": {
        "0": {
            "id": 1,
            "name": "工作",
            "count": 4,
            "tasks": [
                {
                    "id": 1,
                    "user_id": 1,
                    "content": "任务1",
                    "sort": 100000,
                    "sort_s": 10000,
                    "create_date": 1000000,
                    "finish_date": 0,
                    "remove_date": 0
                },
                {
                    "id": 2,
                    "user_id": 1,
                    "content": "任务2",
                    "sort": 100000,
                    "sort_s": 10000,
                    "create_date": 1000000,
                    "finish_date": 0,
                    "remove_date": 0
                },
                {
                    "id": 3,
                    "user_id": 1,
                    "content": "任务3",
                    "sort": 100000,
                    "sort_s": 10000,
                    "create_date": 1000000,
                    "finish_date": 0,
                    "remove_date": 0
                },
                {
                    "id": 4,
                    "user_id": 1,
                    "content": "任务4",
                    "sort": 100000,
                    "sort_s": 10000,
                    "create_date": 1000000,
                    "finish_date": 0,
                    "remove_date": 0
                }
            ]
        },
        "1": {
            "id": 2,
            "name": "生活",
            "count": 1,
            "tasks": [
                {
                    "id": 5,
                    "user_id": 1,
                    "content": "任务5",
                    "sort": 100000,
                    "sort_s": 10000,
                    "create_date": 1000000,
                    "finish_date": 0,
                    "remove_date": 0
                }
            ]
        }
    }
}